dismod_mr/__about__.py
dismod_mr/__init__.py
dismod_mr/data.py
dismod_mr/fit.py
dismod_mr/plot.py
dismod_mr/model/__init__.py
dismod_mr/model/age_groups.py
dismod_mr/model/covariates.py
dismod_mr/model/likelihood.py
dismod_mr/model/ode.py
dismod_mr/model/priors.py
dismod_mr/model/process.py
dismod_mr/model/spline.py
dismod_mr/testing/__init__.py
dismod_mr/testing/data_simulation.py
dismod_mr/testing/example_data/hierarchy.json
dismod_mr/testing/example_data/input_data.csv
dismod_mr/testing/example_data/nodes_to_fit.json
dismod_mr/testing/example_data/output_template.csv
dismod_mr/testing/example_data/parameters.json
dismod_mr-1.1.2.7.dist-info/LICENSE
dismod_mr-1.1.2.7.dist-info/METADATA
dismod_mr-1.1.2.7.dist-info/WHEEL
dismod_mr-1.1.2.7.dist-info/top_level.txt
dismod_mr-1.1.2.7.dist-info/RECORD
