Metadata-Version: 2.1
Name: dismod-mr
Version: 1.1.2.7
Summary: Integrative Meta-Regression Framework for Descriptive Epidemmiology
Home-page: https://github.com/ihmeuw/dismod_mr
Author: Abraham D. Flaxman
Author-email: abie@uw.edu
License: GNU GPLv3
Classifier: Intended Audience :: Developers
Classifier: Intended Audience :: Education
Classifier: Intended Audience :: Science/Research
Classifier: License :: OSI Approved :: GNU General Public License v3 or later (GPLv3+)
Classifier: Natural Language :: English
Classifier: Operating System :: MacOS :: MacOS X
Classifier: Operating System :: POSIX
Classifier: Operating System :: POSIX :: BSD
Classifier: Operating System :: POSIX :: Linux
Classifier: Operating System :: Microsoft :: Windows
Classifier: Programming Language :: Python
Classifier: Programming Language :: Python :: 3.6
Classifier: Programming Language :: Python :: Implementation :: CPython
Classifier: Topic :: Education
Classifier: Topic :: Scientific/Engineering
Classifier: Topic :: Scientific/Engineering :: Mathematics
Classifier: Topic :: Scientific/Engineering :: Medical Science Apps.
Classifier: Topic :: Software Development :: Libraries
License-File: LICENSE
Requires-Dist: numpy (>=1.7.1)
Requires-Dist: scipy (>=0.12.0)
Requires-Dist: pymc (==2.3.8)
Requires-Dist: networkx (==2.3)
Requires-Dist: pandas (<1.1,>=0.23.4)
Requires-Dist: numba (==0.51.0)
Requires-Dist: matplotlib (<3.3)
